model_api/__init__.py
model_api/performance_metrics.py
model_api/adapters/__init__.py
model_api/adapters/inference_adapter.py
model_api/adapters/onnx_adapter.py
model_api/adapters/openvino_adapter.py
model_api/adapters/ovms_adapter.py
model_api/adapters/utils.py
model_api/models/__init__.py
model_api/models/action_classification.py
model_api/models/anomaly.py
model_api/models/classification.py
model_api/models/detection_model.py
model_api/models/image_model.py
model_api/models/instance_segmentation.py
model_api/models/keypoint_detection.py
model_api/models/model.py
model_api/models/sam_models.py
model_api/models/segmentation.py
model_api/models/ssd.py
model_api/models/types.py
model_api/models/utils.py
model_api/models/visual_prompting.py
model_api/models/yolo.py
model_api/models/result/__init__.py
model_api/models/result/anomaly.py
model_api/models/result/base.py
model_api/models/result/classification.py
model_api/models/result/detection.py
model_api/models/result/keypoint.py
model_api/models/result/segmentation.py
model_api/models/result/utils.py
model_api/models/result/visual_prompting.py
model_api/pipelines/__init__.py
model_api/pipelines/async_pipeline.py
model_api/tilers/__init__.py
model_api/tilers/detection.py
model_api/tilers/instance_segmentation.py
model_api/tilers/semantic_segmentation.py
model_api/tilers/tiler.py
model_api/visualizer/__init__.py
model_api/visualizer/visualizer.py
model_api/visualizer/layout/__init__.py
model_api/visualizer/layout/flatten.py
model_api/visualizer/layout/hstack.py
model_api/visualizer/layout/layout.py
model_api/visualizer/primitive/__init__.py
model_api/visualizer/primitive/bounding_box.py
model_api/visualizer/primitive/keypoints.py
model_api/visualizer/primitive/label.py
model_api/visualizer/primitive/overlay.py
model_api/visualizer/primitive/polygon.py
model_api/visualizer/primitive/primitive.py
model_api/visualizer/scene/__init__.py
model_api/visualizer/scene/anomaly.py
model_api/visualizer/scene/classification.py
openvino_model_api-0.3.0.4.dist-info/METADATA
openvino_model_api-0.3.0.4.dist-info/WHEEL
openvino_model_api-0.3.0.4.dist-info/top_level.txt
openvino_model_api-0.3.0.4.dist-info/RECORD
