Metadata-Version: 2.4
Name: openvino_model_api
Version: 0.3.0.4
Summary: Model API: model wrappers and pipelines for inference with OpenVINO
Author: Intel(R) Corporation
Maintainer: Intel(R) Corporation
Project-URL: Homepage, https://github.com/open-edge-platform/model_api
Project-URL: Documentation, https://github.com/open-edge-platform/model_api/blob/master/README.md
Project-URL: Repository, https://github.com/open-edge-platform/model_api.git
Classifier: License :: OSI Approved :: Apache Software License
Classifier: Programming Language :: Python :: 3.10
Requires-Python: >=3.10
Requires-Dist: numpy>=1.16.6
Requires-Dist: opencv-python-headless
Requires-Dist: scipy>=1.5.4
Requires-Dist: openvino>=2025.0
Requires-Dist: pillow
Provides-Extra: ovms
Requires-Dist: tritonclient[http]; extra == "ovms"
Provides-Extra: tests
Requires-Dist: pre-commit; extra == "tests"
Requires-Dist: httpx; extra == "tests"
Requires-Dist: pytest; extra == "tests"
Requires-Dist: pytest-mock; extra == "tests"
Requires-Dist: ultralytics<=8.0.205,>=8.0.114; extra == "tests"
Requires-Dist: onnx; extra == "tests"
Requires-Dist: onnxruntime; extra == "tests"
Provides-Extra: docs
Requires-Dist: myst-parser; extra == "docs"
Requires-Dist: nbsphinx; extra == "docs"
Requires-Dist: pandoc; extra == "docs"
Requires-Dist: sphinx; extra == "docs"
Requires-Dist: sphinx_autodoc_typehints; extra == "docs"
Requires-Dist: pydata-sphinx-theme; extra == "docs"
Requires-Dist: sphinx-copybutton; extra == "docs"
Requires-Dist: sphinx_design; extra == "docs"
Requires-Dist: breathe; extra == "docs"
Requires-Dist: graphviz; extra == "docs"
Provides-Extra: build
Requires-Dist: nanobind==2.8.0; extra == "build"
Provides-Extra: full
Requires-Dist: openvino_model_api[build,dependencies,docs,ovms,tests]; extra == "full"
